nlx/__init__.py
nlx/client.py
nlx/conf/__init__.py
nlx/conf/settings.py
nlx/helpers.py
nlx/main.py
nlx/utils/__init__.py
nlx/utils/dict_utils.py
nlx/utils/misc.py
nlx/utils/module_loading.py
nlx/utils/settings_utils.py
nlx_cli-0.1.5.dist-info/entry_points.txt
nlx_cli-0.1.5.dist-info/LICENSE.txt
nlx_cli-0.1.5.dist-info/WHEEL
nlx_cli-0.1.5.dist-info/METADATA
nlx_cli-0.1.5.dist-info/RECORD
